[
  {
    "action": "move",
    "tree": 24039,
    "parent": 23949,
    "at": 26
  },
  {
    "action": "move",
    "tree": 24052,
    "parent": 23949,
    "at": 25
  },
  {
    "action": "update",
    "tree": 26104,
    "label": "# 1001 \"aof.c\" "
  },
  {
    "action": "update",
    "tree": 27377,
    "label": "# 1165 \"aof.c\" "
  },
  {
    "action": "update",
    "tree": 27971,
    "label": "# 1248 \"aof.c\" "
  },
  {
    "action": "insert",
    "tree": 23905,
    "parent": 23906,
    "at": 1
  },
  {
    "action": "move",
    "tree": 23955,
    "parent": 23905,
    "at": 0
  },
  {
    "action": "move",
    "tree": 23903,
    "parent": 23905,
    "at": 1
  },
  {
    "action": "move",
    "tree": 24015,
    "parent": 23905,
    "at": 2
  },
  {
    "action": "move",
    "tree": 23914,
    "parent": 23904,
    "at": 0
  },
  {
    "action": "move",
    "tree": 25639,
    "parent": 25697,
    "at": 1
  },
  {
    "action": "update",
    "tree": 28939,
    "label": "# 1404 \"aof.c\" "
  },
  {
    "action": "move",
    "tree": 25188,
    "parent": 24870,
    "at": 1
  },
  {
    "action": "move",
    "tree": 25809,
    "parent": 25527,
    "at": 1
  },
  {
    "action": "update",
    "tree": 25800,
    "label": "947"
  },
  {
    "action": "move",
    "tree": 24982,
    "parent": 24971,
    "at": 1
  },
  {
    "action": "update",
    "tree": 24142,
    "label": "744"
  },
  {
    "action": "update",
    "tree": 24589,
    "label": "800"
  },
  {
    "action": "update",
    "tree": 24973,
    "label": "847"
  },
  {
    "action": "update",
    "tree": 25630,
    "label": "916"
  },
  {
    "action": "move",
    "tree": 25083,
    "parent": 25076,
    "at": 1
  },
  {
    "action": "update",
    "tree": 23684,
    "label": "687"
  },
  {
    "action": "update",
    "tree": 23725,
    "label": "689"
  },
  {
    "action": "update",
    "tree": 25074,
    "label": "866"
  },
  {
    "action": "update",
    "tree": 25124,
    "label": "868"
  },
  {
    "action": "update",
    "tree": 25179,
    "label": "871"
  },
  {
    "action": "update",
    "tree": 26775,
    "label": "1072"
  },
  {
    "action": "delete",
    "tree": 23033
  },
  {
    "action": "delete",
    "tree": 23034
  },
  {
    "action": "delete",
    "tree": 23035
  },
  {
    "action": "delete",
    "tree": 23036
  },
  {
    "action": "delete",
    "tree": 23752
  },
  {
    "action": "delete",
    "tree": 23753
  },
  {
    "action": "delete",
    "tree": 23754
  },
  {
    "action": "delete",
    "tree": 23755
  },
  {
    "action": "delete",
    "tree": 23756
  },
  {
    "action": "delete",
    "tree": 23757
  },
  {
    "action": "delete",
    "tree": 23758
  },
  {
    "action": "delete",
    "tree": 23759
  },
  {
    "action": "delete",
    "tree": 23760
  },
  {
    "action": "delete",
    "tree": 23761
  },
  {
    "action": "delete",
    "tree": 23762
  },
  {
    "action": "delete",
    "tree": 23763
  },
  {
    "action": "delete",
    "tree": 23764
  },
  {
    "action": "delete",
    "tree": 23765
  },
  {
    "action": "delete",
    "tree": 23766
  },
  {
    "action": "delete",
    "tree": 23767
  },
  {
    "action": "delete",
    "tree": 23768
  },
  {
    "action": "delete",
    "tree": 23769
  },
  {
    "action": "delete",
    "tree": 23770
  },
  {
    "action": "delete",
    "tree": 23771
  },
  {
    "action": "delete",
    "tree": 23899
  },
  {
    "action": "delete",
    "tree": 23915
  },
  {
    "action": "delete",
    "tree": 23916
  },
  {
    "action": "delete",
    "tree": 23917
  },
  {
    "action": "delete",
    "tree": 23918
  },
  {
    "action": "delete",
    "tree": 23919
  },
  {
    "action": "delete",
    "tree": 23920
  },
  {
    "action": "delete",
    "tree": 23921
  },
  {
    "action": "delete",
    "tree": 23922
  },
  {
    "action": "delete",
    "tree": 23923
  },
  {
    "action": "delete",
    "tree": 23924
  },
  {
    "action": "delete",
    "tree": 23925
  },
  {
    "action": "delete",
    "tree": 23926
  },
  {
    "action": "delete",
    "tree": 23927
  },
  {
    "action": "delete",
    "tree": 23928
  },
  {
    "action": "delete",
    "tree": 23929
  },
  {
    "action": "delete",
    "tree": 23930
  },
  {
    "action": "delete",
    "tree": 23931
  },
  {
    "action": "delete",
    "tree": 23932
  },
  {
    "action": "delete",
    "tree": 23933
  },
  {
    "action": "delete",
    "tree": 23934
  },
  {
    "action": "delete",
    "tree": 23935
  },
  {
    "action": "delete",
    "tree": 23936
  },
  {
    "action": "delete",
    "tree": 23937
  },
  {
    "action": "delete",
    "tree": 23938
  },
  {
    "action": "delete",
    "tree": 23939
  },
  {
    "action": "delete",
    "tree": 23940
  },
  {
    "action": "delete",
    "tree": 23941
  },
  {
    "action": "delete",
    "tree": 23942
  },
  {
    "action": "delete",
    "tree": 23943
  },
  {
    "action": "delete",
    "tree": 23944
  },
  {
    "action": "delete",
    "tree": 23945
  },
  {
    "action": "delete",
    "tree": 23946
  },
  {
    "action": "delete",
    "tree": 23947
  },
  {
    "action": "delete",
    "tree": 23948
  },
  {
    "action": "delete",
    "tree": 23949
  },
  {
    "action": "delete",
    "tree": 23950
  },
  {
    "action": "delete",
    "tree": 23951
  },
  {
    "action": "delete",
    "tree": 23952
  },
  {
    "action": "delete",
    "tree": 23953
  },
  {
    "action": "delete",
    "tree": 23954
  },
  {
    "action": "delete",
    "tree": 23956
  },
  {
    "action": "delete",
    "tree": 23957
  },
  {
    "action": "delete",
    "tree": 23958
  },
  {
    "action": "delete",
    "tree": 23959
  },
  {
    "action": "delete",
    "tree": 23960
  },
  {
    "action": "delete",
    "tree": 23961
  },
  {
    "action": "delete",
    "tree": 23962
  },
  {
    "action": "delete",
    "tree": 23963
  },
  {
    "action": "delete",
    "tree": 23964
  },
  {
    "action": "delete",
    "tree": 23965
  },
  {
    "action": "delete",
    "tree": 23966
  },
  {
    "action": "delete",
    "tree": 23967
  },
  {
    "action": "delete",
    "tree": 23968
  },
  {
    "action": "delete",
    "tree": 23969
  },
  {
    "action": "delete",
    "tree": 23970
  },
  {
    "action": "delete",
    "tree": 23971
  },
  {
    "action": "delete",
    "tree": 23972
  },
  {
    "action": "delete",
    "tree": 23973
  },
  {
    "action": "delete",
    "tree": 23974
  },
  {
    "action": "delete",
    "tree": 23975
  },
  {
    "action": "delete",
    "tree": 23976
  },
  {
    "action": "delete",
    "tree": 23977
  },
  {
    "action": "delete",
    "tree": 23978
  },
  {
    "action": "delete",
    "tree": 23979
  },
  {
    "action": "delete",
    "tree": 23980
  },
  {
    "action": "delete",
    "tree": 23981
  },
  {
    "action": "delete",
    "tree": 23982
  },
  {
    "action": "delete",
    "tree": 23983
  },
  {
    "action": "delete",
    "tree": 23984
  },
  {
    "action": "delete",
    "tree": 23985
  },
  {
    "action": "delete",
    "tree": 23986
  },
  {
    "action": "delete",
    "tree": 23987
  },
  {
    "action": "delete",
    "tree": 23988
  },
  {
    "action": "delete",
    "tree": 23989
  },
  {
    "action": "delete",
    "tree": 23990
  },
  {
    "action": "delete",
    "tree": 23991
  },
  {
    "action": "delete",
    "tree": 23992
  },
  {
    "action": "delete",
    "tree": 23993
  },
  {
    "action": "delete",
    "tree": 23994
  },
  {
    "action": "delete",
    "tree": 23995
  },
  {
    "action": "delete",
    "tree": 23996
  },
  {
    "action": "delete",
    "tree": 23997
  },
  {
    "action": "delete",
    "tree": 23998
  },
  {
    "action": "delete",
    "tree": 23999
  },
  {
    "action": "delete",
    "tree": 24000
  },
  {
    "action": "delete",
    "tree": 24001
  },
  {
    "action": "delete",
    "tree": 24016
  },
  {
    "action": "delete",
    "tree": 24017
  },
  {
    "action": "delete",
    "tree": 24018
  }
]